streamai/__init__.py
streamai/app.py
streamai/alpacalora/__init__.py
streamai/alpacalora/export_hf_checkpoint.py
streamai/alpacalora/export_state_dict_checkpoint.py
streamai/alpacalora/finetune.py
streamai/alpacalora/generate.py
streamai/alpacalora/inference.py
streamai/alpacalora/train.py
streamai/alpacalora/uptest.py
streamai/alpacalora/utils/__init__.py
streamai/alpacalora/utils/callbacks.py
streamai/alpacalora/utils/prompter.py
streamai/llms/__init__.py
streamai/llms/alpacalora.py
streamai/llms/mistral.py
streamai/mistral/__init__.py
streamai/mistral/inference.py
streamai/mistral/mistral7b.py
streamai/mistral/mistral8x7b.py
streamai/mistral/train.py
streamai/mistral/utils/__init__.py
streamai/mistral/utils/callbacks.py
streamai/mistral/utils/prompter.py
streamai/utils/__init__.py
streamai/utils/download.py
streamai/utils/upload.py
streamai-0.1.2.dist-info/LICENSE
streamai-0.1.2.dist-info/METADATA
streamai-0.1.2.dist-info/WHEEL
streamai-0.1.2.dist-info/top_level.txt
streamai-0.1.2.dist-info/RECORD
