Metadata-Version: 2.1
Name: streamai
Version: 0.1.2
Summary: finetune latest open source llms in less than 10 line of code.
Author: Navdeep Dhakar
License: MIT
Classifier: Programming Language :: Python :: 3
Classifier: License :: OSI Approved :: MIT License
Requires-Python: >=3.6
License-File: LICENSE
Requires-Dist: fastapi
Requires-Dist: uvicorn
Requires-Dist: fire
